pyux/__init__.py
pyux/changes.py
pyux/diff.py
pyux/exceptions.py
pyux/sign.py
pyux-0.0.6.dist-info/LICENSE
pyux-0.0.6.dist-info/METADATA
pyux-0.0.6.dist-info/WHEEL
pyux-0.0.6.dist-info/top_level.txt
pyux-0.0.6.dist-info/RECORD
