Metadata-Version: 2.1
Name: pyux
Version: 0.0.6
Summary: Utility to check API integrity in python libraries
Home-page: https://github.com/farizrahman4u/pyux
Author: Fariz Rahman
Author-email: farizrahman4u@gmail.com
License: MIT
Platform: UNKNOWN
